setup.py
distributions/Binomialdistribution.py
distributions/Gaussiandistribution.py
distributions/Generaldistribution.py
distributions/__init__.py
vallabha_distributions.egg-info/PKG-INFO
vallabha_distributions.egg-info/SOURCES.txt
vallabha_distributions.egg-info/dependency_links.txt
vallabha_distributions.egg-info/not-zip-safe
vallabha_distributions.egg-info/top_level.txt